doogat/core/__init__.py
doogat/core/application/use_cases/print_zettel_use_case.py
doogat/core/application/use_cases/read_doogat_use_case.py
doogat/core/domain/entities/__init__.py
doogat/core/domain/entities/project/project.py
doogat/core/domain/entities/project/services/consistency/fixers/fix_lists_bullets.py
doogat/core/domain/entities/project/services/consistency/fixers/normalize_sections_order.py
doogat/core/domain/entities/project/services/consistency/fixers/set_default_completed.py
doogat/core/domain/entities/project/services/consistency/project_zettel_consistency_service.py
doogat/core/domain/entities/project/services/migration/project_zettel_migration_service.py
doogat/core/domain/entities/project/services/migration/upgrades/migrate_loop_log.py
doogat/core/domain/entities/project/services/migration/upgrades/migrate_parent_reference.py
doogat/core/domain/entities/zettel/services/consistency/fixers/align_h1_to_title.py
doogat/core/domain/entities/zettel/services/consistency/fixers/fix_title_format.py
doogat/core/domain/entities/zettel/services/consistency/fixers/remove_duplicate_tags.py
doogat/core/domain/entities/zettel/services/consistency/fixers/set_default_date.py
doogat/core/domain/entities/zettel/services/consistency/fixers/set_default_id.py
doogat/core/domain/entities/zettel/services/consistency/fixers/set_default_processed.py
doogat/core/domain/entities/zettel/services/consistency/fixers/set_default_publish.py
doogat/core/domain/entities/zettel/services/consistency/fixers/set_default_tags.py
doogat/core/domain/entities/zettel/services/consistency/fixers/set_default_title.py
doogat/core/domain/entities/zettel/services/consistency/fixers/set_default_type.py
doogat/core/domain/entities/zettel/services/consistency/fixers/sort_tags.py
doogat/core/domain/entities/zettel/services/consistency/zettel_consistency_service.py
doogat/core/domain/entities/zettel/services/migration/upgrades/move_tag_to_tags.py
doogat_core-0.2.1.dist-info/METADATA
doogat_core-0.2.1.dist-info/WHEEL
doogat_core-0.2.1.dist-info/licenses/LICENSE
doogat_core-0.2.1.dist-info/RECORD
