Metadata-Version: 2.4
Name: doogat-core
Version: 0.2.1
Summary: 
License: GNU GPLv3
License-File: LICENSE
Author: Tomáš Bouška
Author-email: admin@doogat.com
Requires-Python: >=3.12,<4.0
Classifier: License :: Other/Proprietary License
Classifier: Programming Language :: Python :: 3
Classifier: Programming Language :: Python :: 3.12
Classifier: Programming Language :: Python :: 3.13
Classifier: Programming Language :: Python :: 3.14
Requires-Dist: buvis-pybase (>=0.3.0,<1.0.0)
